loopui/__init__.py
loopui/main.py
loopui-0.2.dist-info/licenses/LICENSE
loopui-0.2.dist-info/METADATA
loopui-0.2.dist-info/WHEEL
loopui-0.2.dist-info/top_level.txt
loopui-0.2.dist-info/RECORD
