Metadata-Version: 2.4
Name: loopui
Version: 0.2
Summary: Uncertainty Indicators for ensemble of 3D voxets
Author-email: Guillaume Pirot <guillaume.pirot@uwa.edu.au>
License-Expression: MIT
Project-URL: Homepage, https://github.com/Loop3D/loopUI
Project-URL: Bug Tracker, https://github.com/Loop3D/loopUI/issues
Classifier: Programming Language :: Python :: 3
Classifier: Operating System :: OS Independent
Requires-Python: >=3.9
License-File: LICENSE
Dynamic: license-file
